PyTableWiz/PythonTableWizard.py
PyTableWiz/__init__.py
PyTableWiz-0.0.3.dist-info/LICENSE.txt
PyTableWiz-0.0.3.dist-info/METADATA
PyTableWiz-0.0.3.dist-info/WHEEL
PyTableWiz-0.0.3.dist-info/top_level.txt
PyTableWiz-0.0.3.dist-info/RECORD
