Metadata-Version: 2.1
Name: PyTableWiz
Version: 0.0.3
Summary: Creating tables for CSV data file
Home-page: https://github.com/PramudithRangana/Table-Wizard.git
Author: Pramudith Rangana
Author-email: pramudithrangana@gmail.com
License: MIT
Keywords: CSV,table
Classifier: Operating System :: Microsoft :: Windows
Classifier: License :: OSI Approved :: MIT License
Classifier: Programming Language :: Python :: 3
License-File: LICENSE.txt
